{  
   "Today":[  
      {
         "Equipe1" :"برشلونة",
         "Equipe1_Logo" :"https://a.espncdn.com/combiner/i?img=/i/teamlogos/soccer/500/83.png&w=80&h=80",
         
         "Equipe2" :"غرناطة",
         "Equipe2_Logo" :"https://a.espncdn.com/combiner/i?img=/i/teamlogos/soccer/500/3747.png&w=80&h=80",
         
         "Date" :"19/01",
         "Heure" :"21:00",
         "Competition" :"https://a.espncdn.com/combiner/i?img=/i/leaguelogos/soccer/500/15.png&transparent=true&w=80&h=80"
      },
      {
         "Equipe1" :"إبيزا",
         "Equipe1_Logo" :"https://secure.espncdn.com/combiner/i?img=/i/teamlogos/default-team-logo-500.png&h=244&w=244",
         
         "Equipe2" :"برشلونة",
         "Equipe2_Logo" :"https://a.espncdn.com/combiner/i?img=/i/teamlogos/soccer/500/83.png&w=80&h=80",
         
         "Date" :"22/01",
         "Heure" :"19:00",
         "Competition" :"https://a.espncdn.com/combiner/i?img=/i/leaguelogos/soccer/500/80.png&transparent=true&w=80&h=80"
      },
      {
         "Equipe1" :"فالنسيا",
         "Equipe1_Logo" :"https://ssl.gstatic.com/onebox/media/sports/logos/QPbjvDwI_0Wuu4tCS2O6uw_48x48.png",
         
         "Equipe2" :"برشلونة",
         "Equipe2_Logo" :"https://ssl.gstatic.com/onebox/media/sports/logos/paYnEE8hcrP96neHRNofhQ_48x48.png",
         
         "Date" :"25/01",
         "Heure" :"16:00",
         "Competition" :"https://a.espncdn.com/combiner/i?img=/i/leaguelogos/soccer/500/15.png&transparent=true&w=80&h=80"
      },
      {
         "Equipe1" :"برشلونة",
         "Equipe1_Logo" :"https://a.espncdn.com/combiner/i?img=/i/teamlogos/soccer/500/83.png&w=80&h=80",
         
         "Equipe2" :"ليفانتي",
         "Equipe2_Logo" :"https://a.espncdn.com/combiner/i?img=/i/teamlogos/soccer/500/1538.png&w=80&h=80",
         
         "Date" :"02/02",
         "Heure" :"21:00",
         "Competition" :"https://a.espncdn.com/combiner/i?img=/i/leaguelogos/soccer/500/15.png&transparent=true&w=80&h=80"
      },
      {
         "Equipe1" :"ريال بيتيس",
         "Equipe1_Logo" :"https://a.espncdn.com/combiner/i?img=/i/teamlogos/soccer/500/244.png&w=80&h=80",
         
         "Equipe2" :"برشلونة",
         "Equipe2_Logo" :"https://a.espncdn.com/combiner/i?img=/i/teamlogos/soccer/500/83.png&w=80&h=80",
         
         "Date" :"09/02",
         "Heure" :"21:00",
         "Competition" :"https://a.espncdn.com/combiner/i?img=/i/leaguelogos/soccer/500/15.png&transparent=true&w=80&h=80"
      },
      {
         "Equipe1" :"برشلونة",
         "Equipe1_Logo" :"https://a.espncdn.com/combiner/i?img=/i/teamlogos/soccer/500/83.png&w=80&h=80",
         
         "Equipe2" :"خيتافي",
         "Equipe2_Logo" :"https://a.espncdn.com/combiner/i?img=/i/teamlogos/soccer/500/2922.png&w=80&h=80",
         
         "Date" :"16/02",
         "Heure" :"--:--",
         "Competition" :"https://a.espncdn.com/combiner/i?img=/i/leaguelogos/soccer/500/15.png&transparent=true&w=80&h=80"
      },
      {
         "Equipe1" :"برشلونة",
         "Equipe1_Logo" :"https://a.espncdn.com/combiner/i?img=/i/teamlogos/soccer/500/83.png&w=80&h=80",
         
         "Equipe2" :"إيبار",
         "Equipe2_Logo" :"https://a.espncdn.com/combiner/i?img=/i/teamlogos/soccer/500/3752.png&w=80&h=80",
         
         "Date" :"23/02",
         "Heure" :"--:--",
         "Competition" :"https://a.espncdn.com/combiner/i?img=/i/leaguelogos/soccer/500/15.png&transparent=true&w=80&h=80"
      },
      {
         "Equipe1" :"نابولي",
         "Equipe1_Logo" :"https://a.espncdn.com/combiner/i?img=/i/teamlogos/soccer/500/114.png&w=80&h=80",
         
         "Equipe2" :"برشلونة",
         "Equipe2_Logo" :"https://a.espncdn.com/combiner/i?img=/i/teamlogos/soccer/500/83.png&w=80&h=80",
         
         "Date" :"25/02",
         "Heure" :"21:00",
         "Competition" :"https://a.espncdn.com/combiner/i?img=/i/leaguelogos/soccer/500/2.png&transparent=true&w=80&h=80"
      },
      {
         "Equipe1" :"ريال مدريد",
         "Equipe1_Logo" :"https://a.espncdn.com/combiner/i?img=/i/teamlogos/soccer/500/86.png&w=80&h=80",
         
         "Equipe2" :"برشلونة",
         "Equipe2_Logo" :"https://a.espncdn.com/combiner/i?img=/i/teamlogos/soccer/500/83.png&w=80&h=80",
         
         "Date" :"01/03",
         "Heure" :"--:--",
         "Competition" :"https://a.espncdn.com/combiner/i?img=/i/leaguelogos/soccer/500/15.png&transparent=true&w=80&h=80"
      },
      {
         "Equipe1" :"برشلونة",
         "Equipe1_Logo" :"https://a.espncdn.com/combiner/i?img=/i/teamlogos/soccer/500/83.png&w=80&h=80",
         
         "Equipe2" :"ريال سوسيداد",
         "Equipe2_Logo" :"https://a.espncdn.com/combiner/i?img=/i/teamlogos/soccer/500/89.png&w=80&h=80",
         
         "Date" :"08/03",
         "Heure" :"--:--",
         "Competition" :"https://a.espncdn.com/combiner/i?img=/i/leaguelogos/soccer/500/15.png&transparent=true&w=80&h=80"
      },
      {
         "Equipe1" :"مايوركا",
         "Equipe1_Logo" :"https://a.espncdn.com/combiner/i?img=/i/teamlogos/soccer/500/84.png&w=80&h=80",
         
         "Equipe2" :"برشلونة",
         "Equipe2_Logo" :"https://a.espncdn.com/combiner/i?img=/i/teamlogos/soccer/500/83.png&w=80&h=80",
         
         "Date" :"15/03",
         "Heure" :"--:--",
         "Competition" :"https://a.espncdn.com/combiner/i?img=/i/leaguelogos/soccer/500/15.png&transparent=true&w=80&h=80"
      },
      {
         "Equipe1" :"برشلونة",
         "Equipe1_Logo" :"https://a.espncdn.com/combiner/i?img=/i/teamlogos/soccer/500/83.png&w=80&h=80",
         
         "Equipe2" :"نابولي",
         "Equipe2_Logo" :"https://a.espncdn.com/combiner/i?img=/i/teamlogos/soccer/500/114.png&w=80&h=80",
         
         "Date" :"18/03",
         "Heure" :"21:00",
         "Competition" :"https://a.espncdn.com/combiner/i?img=/i/leaguelogos/soccer/500/2.png&transparent=true&w=80&h=80"
      }
   ]
}
